Test_Load/Demo.py
Test_Load/__init__.py
Test_Load-0.0.1.dist-info/LICENSE
Test_Load-0.0.1.dist-info/METADATA
Test_Load-0.0.1.dist-info/WHEEL
Test_Load-0.0.1.dist-info/top_level.txt
Test_Load-0.0.1.dist-info/RECORD
