Metadata-Version: 2.1
Name: Test-Load
Version: 0.0.1
Summary: Test Load Pip
Home-page: https://github.com/huynhquoc1990/Test_Load.git
Author: Huỳnh Tấn Quốc
Author-email: huynhquoc1990@gamil.com
License: MIT
Platform: UNKNOWN
